brok/__init__.py
brok/__main__.py
brok/main.py
brok-0.0.0.dist-info/LICENSE
brok-0.0.0.dist-info/METADATA
brok-0.0.0.dist-info/WHEEL
brok-0.0.0.dist-info/entry_points.txt
brok-0.0.0.dist-info/top_level.txt
brok-0.0.0.dist-info/RECORD
